tokko_auth_lite/__init__.py
tokko_auth_lite/core.py
tokko_auth_lite/tests.py
tokko_auth_lite/tools/__init__.py
tokko_auth_lite/tools/testing.py
tokko_auth_lite-0.0.2.dist-info/METADATA
tokko_auth_lite-0.0.2.dist-info/WHEEL
tokko_auth_lite-0.0.2.dist-info/top_level.txt
tokko_auth_lite-0.0.2.dist-info/RECORD
