Metadata-Version: 2.1
Name: tokko-auth-lite
Version: 0.0.2
Summary: Tokko Auth2 flavor.
Home-page: https://github.com/TokkoLabs/auth-plugins/tokko_auth_lite.git
Author: Jose Salgado
Author-email: jsalgado@navent.com
License: BSD License
Platform: UNKNOWN
Classifier: Environment :: Web Environment
Classifier: Intended Audience :: Developers
Classifier: License :: OSI Approved :: BSD License
Classifier: Operating System :: OS Independent
Classifier: Programming Language :: Python
Classifier: Programming Language :: Python :: 3.8
Classifier: Topic :: Internet :: WWW/HTTP
Classifier: Topic :: Internet :: WWW/HTTP :: Dynamic Content
Requires-Dist: arrow
Requires-Dist: pyjwt
Requires-Dist: pycrypto
Requires-Dist: python-jwt
Requires-Dist: python-jose
Requires-Dist: PyCryptodome
